flui/__init__.py
flui/app.py
flui/app.scss
flui/cli.py
flui/dna.py
flui/header.py
flui/help.md
flui/py.typed
flui/settings.py
flui/subtype/__init__.py
flui/subtype/counting.py
flui/subtype/data.py
flui/subtype/kmer_index.py
flui/subtype/kmer_set.py
flui/subtype/processing.py
flui_tui-1.5.0.dist-info/METADATA
flui_tui-1.5.0.dist-info/WHEEL
flui_tui-1.5.0.dist-info/entry_points.txt
flui_tui-1.5.0.dist-info/licenses/LICENSE
flui_tui-1.5.0.dist-info/licenses/NOTICE
flui_tui-1.5.0.dist-info/RECORD
