Metadata-Version: 2.4
Name: flui-tui
Version: 1.5.0
Summary: TUI for real-time sub-typing of Avian Flu Viruses
Project-URL: Homepage, https://github.com/dragonfly-science/flui
Project-URL: Repository, https://github.com/dragonfly-science/flui
Project-URL: Issues, https://github.com/dragonfly-science/flui
Author-email: Brett Calcott <brett@dragonfly.co.nz>
License: Apache-2.0
License-File: LICENSE
License-File: NOTICE
Classifier: Development Status :: 4 - Beta
Classifier: Environment :: Console
Classifier: Intended Audience :: Science/Research
Classifier: License :: OSI Approved :: Apache Software License
Classifier: Operating System :: OS Independent
Classifier: Programming Language :: Python :: 3.11
Classifier: Programming Language :: Python :: 3.12
Classifier: Topic :: Scientific/Engineering :: Bio-Informatics
Requires-Python: >=3.11
Requires-Dist: loguru>=0.7.2
Requires-Dist: numpy>=2.1.2
Requires-Dist: platformdirs>=4.3.6
Requires-Dist: pydantic>=2.9.2
Requires-Dist: scipy>=1.14.1
Requires-Dist: textual>=0.84.0
Requires-Dist: typer>=0.12.5
Requires-Dist: watchfiles>=0.24.0
